tuneflow_devkit/__init__.py
tuneflow_devkit/debugger.py
tuneflow_devkit/runner.py
tuneflow_devkit/translate_utils.py
tuneflow_devkit/validation_utils.py
tuneflow_devkit_py-0.8.7.dist-info/LICENSE
tuneflow_devkit_py-0.8.7.dist-info/METADATA
tuneflow_devkit_py-0.8.7.dist-info/WHEEL
tuneflow_devkit_py-0.8.7.dist-info/top_level.txt
tuneflow_devkit_py-0.8.7.dist-info/RECORD
