Metadata-Version: 2.1
Name: tuneflow-devkit-py
Version: 0.8.7
Summary: Implement your music models and algorithms directly in TuneFlow - The next-gen DAW for the AI era
Author-email: Andantei <contact@info.tuneflow.com>
Project-URL: Homepage, https://github.com/tuneflow/tuneflow-devkit-py
Project-URL: Bug Tracker, https://github.com/tuneflow/tuneflow-devkit-py/issues
Keywords: AI,music,DAW,TuneFlow,composition,songwriting,music production,music generation,music transcription,mixing,music theory,music information retrieval,MIR,music analysis,song analysis,SDK,devkit
Classifier: Programming Language :: Python :: 3
Classifier: License :: OSI Approved :: MIT License
Classifier: Operating System :: OS Independent
Requires-Python: >=3.7
License-File: LICENSE
Requires-Dist: python-socketio (>=5.7.2)
Requires-Dist: uvicorn[standard] (>=0.20.0)
Requires-Dist: tuneflow-py (>=0.8.3)
Requires-Dist: msgpack (==1.0.4)
Requires-Dist: fastapi (==0.92.0)
Requires-Dist: msgpack-asgi (==1.1.0)
